[
  {
    "id": 1,
    "name": "Budowa i infrastruktura",
    "subCategories": [
      {
        "id": 2,
        "name": "Prace konstrukcyjne",
        "subCategories": [],
        "slug": "prace_konstrukcyjne"
      },
      {
        "id": 3,
        "name": "Roboty ziemne",
        "subCategories": [],
        "slug": "roboty_ziemne"
      },
      {
        "id": 4,
        "name": "Remonty i modernizacje",
        "subCategories": [],
        "slug": "remonty_i_modernizacje"
      },
      {
        "id": 5,
        "name": "Montaż elementów budowlanych",
        "subCategories": [],
        "slug": "montaz_elementow_budowlanych"
      }
    ],
    "slug": "budowa_i_infrastruktura"
  },
  {
    "id": 6,
    "name": "Utrzymanie techniczne",
    "subCategories": [
      {
        "id": 7,
        "name": "Instalacje sanitarne i grzewcze",
        "subCategories": [],
        "slug": "instalacje_sanitarne_i_grzewcze"
      },
      {
        "id": 8,
        "name": "Sieci elektryczne i oświetlenie",
        "subCategories": [],
        "slug": "sieci_elektryczne_i_oswietlenie"
      },
      {
        "id": 9,
        "name": "Systemy HVAC",
        "subCategories": [],
        "slug": "systemy_hvac"
      },
      {
        "id": 10,
        "name": "Systemy BMS/automatyka",
        "subCategories": [],
        "slug": "systemy_bms_automatyka"
      }
    ],
    "slug": "utrzymanie_techniczne"
  },
  {
    "id": 11,
    "name": "Usługi „miękkie”",
    "subCategories": [
      {
        "id": 12,
        "name": "Sprzątanie i higiena",
        "subCategories": [],
        "slug": "sprzatanie_i_higiena"
      },
      {
        "id": 13,
        "name": "Catering i vending",
        "subCategories": [],
        "slug": "catering_i_vending"
      },
      {
        "id": 14,
        "name": "Obsługa recepcyjna i concierge",
        "subCategories": [],
        "slug": "obsluga_recepcyjna_i_concierge"
      },
      {
        "id": 15,
        "name": "Zarządzanie odpadami",
        "subCategories": [],
        "slug": "zarzadzanie_odpadami"
      }
    ],
    "slug": "uslugi_miekkie"
  },
  {
    "id": 16,
    "name": "Tereny zewnętrzne i zieleniarskie",
    "subCategories": [
      {
        "id": 17,
        "name": "Pielęgnacja ogrodów",
        "subCategories": [],
        "slug": "pielegnacja_ogrodow"
      },
      {
        "id": 18,
        "name": "Pielęgnacja parkingu",
        "subCategories": [],
        "slug": "pielegnacja_parkingu"
      },
      {
        "id": 19,
        "name": "Mała architektura",
        "subCategories": [],
        "slug": "mala_architektura"
      },
      {
        "id": 20,
        "name": "Nawierzchnie komunikacyjne",
        "subCategories": [],
        "slug": "nawierzchnie_komunikacyjne"
      },
      {
        "id": 21,
        "name": "Oświetlenie zewnętrzne",
        "subCategories": [],
        "slug": "oswietlenie_zewnetrzne"
      }
    ],
    "slug": "tereny_zewnetrzne_i_zieleniarskie"
  },
  {
    "id": 22,
    "name": "Cyfrowe i IT",
    "subCategories": [
      {
        "id": 23,
        "name": "Strony internetowe i e‑commerce",
        "subCategories": [],
        "slug": "strony_internetowe_i_e_commerce"
      },
      {
        "id": 24,
        "name": "Systemy PMS/CRS",
        "subCategories": [],
        "slug": "systemy_pms_crs"
      },
      {
        "id": 25,
        "name": "Sieci LAN/Wi‑Fi i bezpieczeństwo IT",
        "subCategories": [],
        "slug": "sieci_lan_wi_fi_i_bezpieczenstwo_it"
      },
      {
        "id": 26,
        "name": "Rozwiązania IoT",
        "subCategories": [],
        "slug": "rozwiazania_iot"
      }
    ],
    "slug": "cyfrowe_i_it"
  },
  {
    "id": 27,
    "name": "Projektowanie wnętrz i wyposażenie",
    "subCategories": [
      {
        "id": 28,
        "name": "Projektowanie graficzne i 3D",
        "subCategories": [],
        "slug": "projektowanie_graficzne_i_3d"
      },
      {
        "id": 29,
        "name": "Dobór mebli i dekoracji",
        "subCategories": [],
        "slug": "dobor_mebli_i_dekoracji"
      },
      {
        "id": 30,
        "name": "Oświetlenie wewnętrzne",
        "subCategories": [],
        "slug": "oswietlenie_wewnetrzne"
      },
      {
        "id": 31,
        "name": "Tekstylia hotelowe",
        "subCategories": [],
        "slug": "tekstylia_hotelowe"
      }
    ],
    "slug": "projektowanie_wnetrz_i_wyposazenie"
  },
  {
    "id": 32,
    "name": "Konsulting i szkolenia",
    "subCategories": [
      {
        "id": 33,
        "name": "Szkolenia personelu",
        "subCategories": [],
        "slug": "szkolenia_personelu"
      },
      {
        "id": 34,
        "name": "Doradztwo prawne i compliance",
        "subCategories": [],
        "slug": "doradztwo_prawne_i_compliance"
      },
      {
        "id": 35,
        "name": "Zarządzanie ESG",
        "subCategories": [],
        "slug": "zarzadzanie_esg"
      }
    ],
    "slug": "konsulting_i_szkolenia"
  },
  {
    "id": 36,
    "name": "Zarządzanie energią i zrównoważony rozwój",
    "subCategories": [
      {
        "id": 37,
        "name": "Instalacje fotowoltaiczne",
        "subCategories": [],
        "slug": "instalacje_fotowoltaiczne"
      },
      {
        "id": 38,
        "name": "Systemy smart meteringu",
        "subCategories": [],
        "slug": "systemy_smart_meteringu"
      },
      {
        "id": 39,
        "name": "Programy oszczędnościowe",
        "subCategories": [],
        "slug": "programy_oszczednosciowe"
      }
    ],
    "slug": "zarzadzanie_energia_i_zrownowazony_rozwoj"
  },
  {
    "id": 40,
    "name": "Bezpieczeństwo i ochrona",
    "subCategories": [
      {
        "id": 41,
        "name": "Monitoring CCTV",
        "subCategories": [],
        "slug": "monitoring_cctv"
      },
      {
        "id": 42,
        "name": "Kontrola dostępu",
        "subCategories": [],
        "slug": "kontrola_dostepu"
      },
      {
        "id": 43,
        "name": "Systemy przeciwpożarowe",
        "subCategories": [],
        "slug": "systemy_przeciwpozarowe"
      },
      {
        "id": 44,
        "name": "Przeglądy BHP",
        "subCategories": [],
        "slug": "przeglady_bhp"
      }
    ],
    "slug": "bezpieczenstwo_i_ochrona"
  },
  {
    "id": 45,
    "name": "Marketing i branding",
    "subCategories": [
      {
        "id": 46,
        "name": "Kampanie online (SEM/SEO, social media)",
        "subCategories": [],
        "slug": "kampanie_online_sem_seo_social_media"
      },
      {
        "id": 47,
        "name": "Fotografia i wirtualne spacery",
        "subCategories": [],
        "slug": "fotografia_i_wirtualne_spacery"
      },
      {
        "id": 48,
        "name": "Content marketing",
        "subCategories": [],
        "slug": "content_marketing"
      },
      {
        "id": 49,
        "name": "Programy lojalnościowe",
        "subCategories": [],
        "slug": "programy_lojalnosciowe"
      }
    ],
    "slug": "marketing_i_branding"
  },
  {
    "id": 50,
    "name": "Audyty",
    "subCategories": [
      {
        "id": 51,
        "name": "Audyty personelu",
        "subCategories": [],
        "slug": "audyty_personelu"
      },
      {
        "id": 52,
        "name": "Audyty budynku",
        "subCategories": [],
        "slug": "audyty_budynku"
      },
      {
        "id": 53,
        "name": "Audyty systemów",
        "subCategories": [],
        "slug": "audyty_systemow"
      },
      {
        "id": 54,
        "name": "Audyty prawne",
        "subCategories": [],
        "slug": "audyty_prawne"
      }
    ],
    "slug": "audyty"
  }
]